verysimplemodule987654321/__init__.py
verysimplemodule987654321/add.py
verysimplemodule987654321/subtract.py
verysimplemodule987654321/extras/__init__.py
verysimplemodule987654321/extras/divide.py
verysimplemodule987654321/extras/multiply.py
verysimplemodule987654321-0.0.3.dist-info/METADATA
verysimplemodule987654321-0.0.3.dist-info/WHEEL
verysimplemodule987654321-0.0.3.dist-info/top_level.txt
verysimplemodule987654321-0.0.3.dist-info/RECORD
